{
    "questions": [
      {
        "questionz": {
          "id": 1,
          "question": "a question here",
          "answer": 3,
          "ver": 1,
          "choice_one": "there something on my mind",
          "choice_two": "there is nothing on my mind",
          "choice_three": "what do you tink?",
          "choice_four": "No more"
        }
      },
      {
        "questionz": {
          "id": 1,
          "question": "a question here",
          "answer": 3,
          "ver": 1,
          "choice_one": "there something on my mind",
          "choice_two": "there is nothing on my mind",
          "choice_three": "what do you tink?",
          "choice_four": "No more"
        }
      },
      {
        "questionz": {
          "id": 1,
          "question": "a questioen here",
          "answer": 3,
          "ver": 1,
          "choice_one": "there something on my mind",
          "choice_two": "there is nothing on my mind",
          "choice_three": "what do you tink?",
          "choice_four": "No more"
        }
      },
      {
        "questionz": {
          "id": 1,
          "question": "a questfion here",
          "answer": 3,
          "ver": 1,
          "choice_one": "theresd something on my mind",
          "choice_two": "there is nosthing on my mind",
          "choice_three": "what do yodau tink?",
          "choice_four": "No mosdre"
        }
      },
      {
        "questionz": {
          "id": 1,
          "question": "a questionsds here",
          "answer": 3,
          "ver": 1,
          "choice_one": "there saomething on my mind",
          "choice_two": "there is nsdothing on my mind",
          "choice_three": "what do you tfink?",
          "choice_four": "Nofd more"
        }
      },
      {
        "questionz": {
          "id": 1,
          "question": "a quddestion here",
          "answer": 3,
          "ver": 1,
          "choice_one": "there ffomething on my mind",
          "choice_two": "there is nothingffon my mind",
          "choice_three": "what do youff tink?",
          "choice_four": "No more"
        }
      },
      {
        "questionz": {
          "id": 1,
          "question": "a questiffon here",
          "answer": 3,
          "ver": 1,
          "choice_one": "there sffomething on my mind",
          "choice_two": "there is notffhing on my mind",
          "choice_three": "what do ffyou tink?",
          "choice_four": "No ffmore"
        }
      },
      {
        "questionz": {
          "id": 1,
          "question": "a questionff here",
          "answer": 3,
          "ver": 1,
          "choice_one": "thereff something on my mind",
          "choice_two": "theffre is nothing on my mind",
          "choice_three": "whafft do you tink?",
          "choice_four": "No morffe"
        }
      },
      {
        "questionz": {
          "id": 1,
          "question": "a quffestion here",
          "answer": 3,
          "ver": 1,
          "choice_one": "tfhere sffomething on my mind",
          "choice_two": "thefre isffnothing on my mind",
          "choice_three": "whffat dffo you tink?",
          "choice_four": "fo mffore"
        }
      }
    ]
  }